<annotation>
	<folder>Datasets4</folder>
	<filename>poor_198.jpg</filename>
	<path>/media/hildan/AdhenTamvanDanVemverani/Anotasi/Datasets4/poor_198.jpg</path>
	<source>
		<database>Unknown</database>
	</source>
	<size>
		<width>600</width>
		<height>600</height>
		<depth>3</depth>
	</size>
	<segmented>0</segmented>
	<object>
		<name>Retak</name>
		<pose>Unspecified</pose>
		<truncated>0</truncated>
		<difficult>0</difficult>
		<bndbox>
			<xmin>276</xmin>
			<ymin>432</ymin>
			<xmax>323</xmax>
			<ymax>588</ymax>
		</bndbox>
	</object>
	<object>
		<name>Retak</name>
		<pose>Unspecified</pose>
		<truncated>0</truncated>
		<difficult>0</difficult>
		<bndbox>
			<xmin>83</xmin>
			<ymin>468</ymin>
			<xmax>191</xmax>
			<ymax>586</ymax>
		</bndbox>
	</object>
	<object>
		<name>Retak</name>
		<pose>Unspecified</pose>
		<truncated>0</truncated>
		<difficult>0</difficult>
		<bndbox>
			<xmin>435</xmin>
			<ymin>481</ymin>
			<xmax>541</xmax>
			<ymax>581</ymax>
		</bndbox>
	</object>
</annotation>
